sequential-circuits/upcounter/upc.v
module counter(input clk, input rstn, output reg[3:0] out);
always @(posedge clk) begin
    if (! rstn)
    out <= 0;
    else
    out <= out + 1;
end
endmodule

sequential-circuits/upcounter/tb_upc.v
module tb_counter;
reg clk;
reg rstn;
wire [3:0] out;

counter c0 (.clk(clk), .rstn(rstn), .out(out));
always #5 clk = ~clk;

initial begin
    clk <= 0;
rstn <= 0;

#20 rstn <= 1;
#80 rstn <= 1;
#50 rstn <= 1;

#20 $finish;

    end
    initial begin
		$monitor("@:%0t :: rstn:%0b, clk:%0b, out:%0b", $time, rstn, clk, out);
	end

        initial begin
        $dumpfile("upc.vcd");
        $dumpvars(1);
    end
    
endmodule

sequential-circuits/upcounter/upc.vcd
$date
	Sat Nov 06 06:56:11 2021
$end
$version
	Icarus Verilog
$end
$timescale
	1s
$end
$scope module tb_counter $end
$var wire 4 ! out [3:0] $end
$var reg 1 " clk $end
$var reg 1 # rstn $end
$upscope $end
$enddefinitions $end
#0
$dumpvars
0#
0"
bx !
$end
#5
b0 !
1"
#10
0"
#15
1"
#20
1#
0"
#25
b1 !
1"
#30
0"
#35
b10 !
1"
#40
0"
#45
b11 !
1"
#50
0"
#55
b100 !
1"
#60
0"
#65
b101 !
1"
#70
0"
#75
b110 !
1"
#80
0"
#85
b111 !
1"
#90
0"
#95
b1000 !
1"
#100
0"
#105
b1001 !
1"
#110
0"
#115
b1010 !
1"
#120
0"
#125
b1011 !
1"
#130
0"
#135
b1100 !
1"
#140
0"
#145
b1101 !
1"
#150
0"
#155
b1110 !
1"
#160
0"
#165
b1111 !
1"
